gryphon_pusherclient-0.2.1.dist-info/METADATA
gryphon_pusherclient-0.2.1.dist-info/RECORD
gryphon_pusherclient-0.2.1.dist-info/WHEEL
gryphon_pusherclient-0.2.1.dist-info/top_level.txt
pusherclient/__init__.py
pusherclient/channel.py
pusherclient/connection.py
